lycium/__init__.py
lycium/accesscontrol.py
lycium/amqplib.py
lycium/asynchttphandler.py
lycium/asyncrequest.py
lycium/behaviors.py
lycium/cacheproxy.py
lycium/dbproxy.py
lycium/elasticsearchsaver.py
lycium/exceptionreporter.py
lycium/guniapp.py
lycium/modelutils.py
lycium/registerroute.py
lycium/singleton.py
lycium/supports.py
lycium/webapplication.py
lycium/kafka/__init__.py
lycium/kafka/asyncWrapper.py
lycium/kafka/client.py
lycium/kafka/consumerHelper.py
lycium/kafka/debugSet.py
lycium/kafka/helper.py
lycium/kafka/kafkaWorker.py
lycium/kafka/logger.py
lycium/kafka/producerHelper.py
lycium/kafka/publishesMessage.py
lycium/kafka/server.py
lycium/kafka/workerDelegate.py
lycium/kafka/protocol/__init__.py
lycium/kafka/protocol/kafkapacket_pb2.py
lycium/microsvc/__init__.py
lycium/microsvc/applicationServer.py
lycium/microsvc/context.py
lycium/microsvc/router.py
lycium/microsvc/utils.py
lycium/microsvc/middlewares/__init__.py
lycium/microsvc/middlewares/exceptionMiddleware.py
lycium/microsvc/middlewares/logMiddleware.py
lycium/microsvc/middlewares/websocketPackageMiddleware.py
lycium/microsvc/protocol/__init__.py
lycium/microsvc/protocol/packagewrapper_pb2.py
lycium/sqlalchemy_dialects/__init__.py
lycium/sqlalchemy_dialects/asyncpg_migrate/__init__.py
lycium/sqlalchemy_dialects/sync_threading/__init__.py
lycium/sqlalchemy_dialects/sync_threading/asyncio.py
lycium/sqlalchemy_dialects/sync_threading/base.py
lycium/sqlalchemy_dialects/sync_threading/exc.py
lycium/tornadoadapts/__init__.py
lycium/tornadoadapts/stack_context.py
lycium/tornadozeep/__init__.py
lycium/tornadozeep/bindings.py
lycium/tornadozeep/transport.py
lycium/utilities/__init__.py
lycium/utilities/aescoder.py
lycium/utilities/descoder.py
lycium/utilities/fileutil.py
lycium/utilities/htmldocutils.py
lycium/utilities/img_utils.py
lycium/utilities/iplist.py
lycium/utilities/notifydata_utils.py
lycium/utilities/orderutil.py
lycium/utilities/restful_api.py
lycium/utilities/rsacoder.py
lycium-0.2.25.dist-info/LICENCE
lycium-0.2.25.dist-info/METADATA
lycium-0.2.25.dist-info/WHEEL
lycium-0.2.25.dist-info/top_level.txt
lycium-0.2.25.dist-info/RECORD
