Metadata-Version: 2.1
Name: lycium
Version: 0.2.25
Summary: Common python package
Home-page: https://gitee.com/starview/lycium
Author: kevinyjn
Author-email: kevinyjn@foxmail.com
Classifier: Programming Language :: Python :: 3
Classifier: License :: OSI Approved :: MIT License
Classifier: Operating System :: OS Independent
Requires-Python: >=3.6
License-File: LICENCE
Requires-Dist: pycrypto
Requires-Dist: blinker
Requires-Dist: pika
Requires-Dist: redis
Requires-Dist: gunicorn
Requires-Dist: mongoengine
Requires-Dist: elasticsearch ==7.12.0
Requires-Dist: sqlalchemy ==1.4.25
Requires-Dist: sshtunnel
Requires-Dist: Cython
Requires-Dist: IPy
Requires-Dist: requests
Requires-Dist: tornado
Requires-Dist: zeep[async]
Requires-Dist: motor
Requires-Dist: aredis
Requires-Dist: pyopenssl
Requires-Dist: rsa
Requires-Dist: cx-Oracle
Requires-Dist: asyncpg
Requires-Dist: aiomysql
Requires-Dist: aiosqlite
Requires-Dist: pymssql
Requires-Dist: protobuf ==3.14.0
Requires-Dist: confluent-kafka
Requires-Dist: PyJWT
Requires-Dist: pymongo ==3.12.1
